<?xml version = '1.0' encoding = 'UTF-8'?>
<TableProxyOraclev11g class="oracle.dbtools.crest.model.design.storage.oracle.v11g.TableProxyOraclev11g" name="Estudiante" directorySegmentName="seg_0" id="5C727F5C-B195-1234-22D6-95D0038B7B33">
<createdBy>oliversaraguro</createdBy>
<createdTime>2024-05-11 02:46:28 UTC</createdTime>
<ownerDesignName>EscuelaArtesMarciales</ownerDesignName>
<logging>YES</logging>
<partitionedRowMovement>DISABLE</partitionedRowMovement>
<temporaryChanged>false</temporaryChanged>
<accessDriverType>oracle_loader</accessDriverType>
<rejectLimit></rejectLimit>
<columnProxies itemClass="oracle.dbtools.crest.model.design.storage.oracle.v12c.ColumnProxyOraclev12c">
<ColumnProxy name="idEstudiante" id="030EBEBE-8CC7-5FF3-389E-CEFA319FF0E5">
<createdBy>oliversaraguro</createdBy>
<createdTime>2024-05-11 02:46:28 UTC</createdTime>
<ownerDesignName>EscuelaArtesMarciales</ownerDesignName>
</ColumnProxy>
<ColumnProxy name="observaciones" id="66AE53EA-48E6-7C69-A0C1-3520CC4CC081">
<createdBy>oliversaraguro</createdBy>
<createdTime>2024-05-11 02:46:28 UTC</createdTime>
<ownerDesignName>EscuelaArtesMarciales</ownerDesignName>
</ColumnProxy>
<ColumnProxy name="Persona_cedula" id="BA9AE6CD-70CE-BD8E-C0BA-D26CF8E7994A">
<createdBy>oliversaraguro</createdBy>
<createdTime>2024-05-11 02:46:28 UTC</createdTime>
<ownerDesignName>EscuelaArtesMarciales</ownerDesignName>
</ColumnProxy>
</columnProxies>
<foreignKeys>
<ForeignKey class="oracle.dbtools.crest.model.design.storage.oracle.v10g.FKProxyOraclev10g" name="Estudiante_Persona_FK" id="06DD919F-4D70-22D0-2D7C-00E7C8AE176A">
<createdBy>oliversaraguro</createdBy>
<createdTime>2024-05-11 02:46:28 UTC</createdTime>
<ownerDesignName>EscuelaArtesMarciales</ownerDesignName>
</ForeignKey>
</foreignKeys>
<primaryKeys>
<PrimaryKey class="oracle.dbtools.crest.model.design.storage.oracle.v10g.PKProxyOraclev10g" name="Estudiante_PK" id="64330BCB-4E36-E5E0-78A5-D56C243D1386">
<createdBy>oliversaraguro</createdBy>
<createdTime>2024-05-11 02:46:28 UTC</createdTime>
<ownerDesignName>EscuelaArtesMarciales</ownerDesignName>
<indexSort>SORTED</indexSort>
</PrimaryKey>
</primaryKeys>
</TableProxyOraclev11g>